OBP_security_pillar_2/__init__.py
OBP_security_pillar_2/compliance.py
OBP_security_pillar_2/elb_logging_enabled.py
OBP_security_pillar_2/elb_tls_https_listeners_only.py
OBP_security_pillar_2/guard_duty_enabled.py
OBP_security_pillar_2/lambda_inside_vpc.py
OBP_security_pillar_2/security_hub_enabled.py
OBP_security_pillar_2/auto_scaling/__init__.py
OBP_security_pillar_2/auto_scaling/launch_config_public_ip_disabled.py
OBP_security_pillar_2/cloudtrail/__init__.py
OBP_security_pillar_2/cloudtrail/cloudtrail_cloudwatch_logs_enabled.py
OBP_security_pillar_2/cloudtrail/driver.py
OBP_security_pillar_2/dynamodb/__init__.py
OBP_security_pillar_2/dynamodb/dynamodb_table_encrypted_kms.py
OBP_security_pillar_2/ec2/Incoming_ssh_disabled.py
OBP_security_pillar_2/ec2/__init__.py
OBP_security_pillar_2/ec2/ebs_snapshot_public_restorable_check.py
OBP_security_pillar_2/ec2/ec2_ebs_encryption_by_default.py
OBP_security_pillar_2/ec2/ec2_encrypted_volume.py
OBP_security_pillar_2/ec2/ec2_imdsv2_check.py
OBP_security_pillar_2/ec2/ec2_instance_managed_by_ssm.py
OBP_security_pillar_2/ec2/ec2_instance_multiple_eni_check.py
OBP_security_pillar_2/ec2/ec2_instance_profile_attached.py
OBP_security_pillar_2/ec2/ec2_volume_inuse_check.py
OBP_security_pillar_2/ec2/instance_in_vpc.py
OBP_security_pillar_2/ec2/vpc_flow_logs_enabled.py
OBP_security_pillar_2/rds/__init__.py
OBP_security_pillar_2/rds/rds_automatic_minor_version_upgrade_enabled.py
OBP_security_pillar_2/rds/rds_instance_public_access_check.py
OBP_security_pillar_2/rds/rds_snapshot_encrypted.py
OBP_security_pillar_2/rds/rds_snapshots_public_prohibited.py
OBP_security_pillar_2/rds/rds_storage_encrypted.py
OBP_security_pillar_2/s3/__init__.py
OBP_security_pillar_2/s3/s3_bucket_logging_enabled.py
OBP_security_pillar_2/s3/s3_bucket_public_read_prohibited.py
OBP_security_pillar_2/s3/s3_bucket_public_write_prohibited.py
OBP_security_pillar_2/s3/s3_bucket_server_side_encryption_enabled.py
OBP_security_pillar_2/s3/s3_bucket_ssl_requests_only.py
OBP_security_pillar_2-0.0.4.dist-info/METADATA
OBP_security_pillar_2-0.0.4.dist-info/WHEEL
OBP_security_pillar_2-0.0.4.dist-info/top_level.txt
OBP_security_pillar_2-0.0.4.dist-info/RECORD
